django_osm_widgets/__init__.py
django_osm_widgets/static/django_osm_widgets/LatLonOpenlayersOSMWidget.js
django_osm_widgets/templates/django_osm_widgets/latlon-openlayers-osm.html
django_osm_widgets/templates/django_osm_widgets/openlayers-osm.html
django_osm_widgets/templates/django_osm_widgets/openlayers.html
django_osm_widgets/widgets.py
django_osm_widgets-0.0.4.dist-info/LICENSE
django_osm_widgets-0.0.4.dist-info/METADATA
django_osm_widgets-0.0.4.dist-info/WHEEL
django_osm_widgets-0.0.4.dist-info/RECORD
