Metadata-Version: 2.3
Name: django-osm-widgets
Version: 0.0.4
Summary: Improved widgets for Django's PointField
License: BSD-3-Clause
Author: Kapt
Author-email: dev@kapt.mobi
Requires-Python: >=3.10
Classifier: License :: OSI Approved :: BSD License
Classifier: Programming Language :: Python :: 3
Classifier: Programming Language :: Python :: 3.10
Classifier: Programming Language :: Python :: 3.11
Classifier: Programming Language :: Python :: 3.12
Classifier: Programming Language :: Python :: 3.13
Requires-Dist: Django (>=3.0,<5.2)
Project-URL: Repository, https://gitlab.com/kapt/open-source/django-osm-widgets
